actorch-0.0.5.dist-info/NOTICE
actorch-0.0.5.dist-info/RECORD
actorch-0.0.5.dist-info/top_level.txt
actorch-0.0.5.dist-info/WHEEL
actorch-0.0.5.dist-info/entry_points.txt
actorch-0.0.5.dist-info/LICENSE
actorch-0.0.5.dist-info/METADATA
actorch/__init__.py
actorch/__main__.py
actorch/py.typed
actorch/version.py
actorch/optimizers/__init__.py
actorch/optimizers/cgbls.py
actorch/algorithms/__init__.py
actorch/algorithms/ppo.py
actorch/algorithms/utils.py
actorch/algorithms/d3pg.py
actorch/algorithms/acktr.py
actorch/algorithms/td3.py
actorch/algorithms/algorithm.py
actorch/algorithms/sac.py
actorch/algorithms/a2c.py
actorch/algorithms/trpo.py
actorch/algorithms/ddpg.py
actorch/algorithms/awr.py
actorch/algorithms/reinforce.py
actorch/algorithms/value_estimation/monte_carlo_return.py
actorch/algorithms/value_estimation/__init__.py
actorch/algorithms/value_estimation/off_policy_lambda_return.py
actorch/algorithms/value_estimation/n_step_return.py
actorch/algorithms/value_estimation/utils.py
actorch/algorithms/value_estimation/retrace.py
actorch/algorithms/value_estimation/lambda_return.py
actorch/algorithms/value_estimation/tree_backup.py
actorch/algorithms/value_estimation/importance_sampling.py
actorch/algorithms/value_estimation/generalized_estimator.py
actorch/algorithms/value_estimation/vtrace.py
actorch/models/__init__.py
actorch/models/fc_net.py
actorch/models/conv_net.py
actorch/models/model.py
actorch/models/lstm_net.py
actorch/models/hydra.py
actorch/models/modules/__init__.py
actorch/models/modules/broadcast_cat.py
actorch/models/modules/parameter_module.py
actorch/schedules/constant_schedule.py
actorch/schedules/exponential_schedule.py
actorch/schedules/__init__.py
actorch/schedules/lambda_schedule.py
actorch/schedules/linear_schedule.py
actorch/schedules/schedule.py
actorch/utils/__init__.py
actorch/utils/future_ref.py
actorch/utils/common.py
actorch/utils/checkpointable_mixin.py
actorch/resources/__init__.py
actorch/resources/styles/__init__.py
actorch/resources/styles/default-style.mplstyle
actorch/resources/templates/__init__.py
actorch/resources/templates/default-template.yml
actorch/samplers/__init__.py
