Metadata-Version: 2.1
Name: actorch
Version: 0.0.5
Summary: Deep reinforcement learning framework for fast prototyping based on PyTorch
Home-page: https://github.com/lucadellalib/actorch
Author: Luca Della Libera
Author-email: luca.dellalib@gmail.com
License: Apache License 2.0
Keywords: Deep reinforcement learning,PyTorch
Platform: OS Independent
Classifier: Development Status :: 3 - Alpha
Classifier: Environment :: Console
Classifier: Environment :: GPU :: NVIDIA CUDA
Classifier: Intended Audience :: Developers
Classifier: Intended Audience :: Information Technology
Classifier: Intended Audience :: Science/Research
Classifier: License :: OSI Approved :: Apache Software License
Classifier: Natural Language :: English
Classifier: Operating System :: OS Independent
Classifier: Programming Language :: Python :: 3
Classifier: Programming Language :: Python :: 3.6
Classifier: Programming Language :: Python :: 3.7
Classifier: Programming Language :: Python :: 3.8
Classifier: Programming Language :: Python :: 3.9
Classifier: Programming Language :: Python :: 3.10
Classifier: Programming Language :: Python :: 3 :: Only
Classifier: Topic :: Scientific/Engineering :: Artificial Intelligence
Classifier: Topic :: Software Development :: Libraries :: Python Modules
Classifier: Typing :: Typed
Requires-Python: >=3.6
License-File: LICENSE
License-File: NOTICE
Requires-Dist: cloudpickle (>=1.3.0)
Requires-Dist: colorama (>=0.4.3)
Requires-Dist: GPUtil (>=1.4.0)
Requires-Dist: gymnasium (>=0.26.1)
Requires-Dist: numpy (>=1.19.5)
Requires-Dist: psutil (>=5.7.0)
Requires-Dist: PyYAML (>=5.3.1)
Requires-Dist: ray[tune] (<2.*,>=1.13.0)
Requires-Dist: scipy (>=1.4.1)
Requires-Dist: tensorboard (>=2.6.0)
Requires-Dist: torch (>=1.12.0)
Provides-Extra: all
Requires-Dist: matplotlib (>=3.2.1) ; extra == 'all'
Requires-Dist: numpy (>=1.19.5) ; extra == 'all'
Requires-Dist: plotly (>=4.9.0) ; extra == 'all'
Requires-Dist: PyYAML (>=5.3.1) ; extra == 'all'
Requires-Dist: scipy (>=1.4.1) ; extra == 'all'
Requires-Dist: tensorboard (>=2.6.0) ; extra == 'all'
Requires-Dist: tqdm (>=4.48.2) ; extra == 'all'
Requires-Dist: pytest (>=5.4.3) ; extra == 'all'
Requires-Dist: pytest-cov (>=2.9.0) ; extra == 'all'
Requires-Dist: black (>=22.3.0) ; extra == 'all'
Requires-Dist: cibuildwheel (>=2.3.1) ; extra == 'all'
Requires-Dist: flake8 (>=3.8.3) ; extra == 'all'
Requires-Dist: flake8-bugbear (>=20.1.4) ; extra == 'all'
Requires-Dist: isort (>=5.4.2) ; extra == 'all'
Requires-Dist: mypy (>=0.812) ; extra == 'all'
Requires-Dist: pre-commit (>=2.6.0) ; extra == 'all'
Requires-Dist: pre-commit-hooks (>=3.2.0) ; extra == 'all'
Requires-Dist: twine (>=3.3.0) ; extra == 'all'
Provides-Extra: dev
Requires-Dist: black (>=22.3.0) ; extra == 'dev'
Requires-Dist: cibuildwheel (>=2.3.1) ; extra == 'dev'
Requires-Dist: flake8 (>=3.8.3) ; extra == 'dev'
Requires-Dist: flake8-bugbear (>=20.1.4) ; extra == 'dev'
Requires-Dist: isort (>=5.4.2) ; extra == 'dev'
Requires-Dist: mypy (>=0.812) ; extra == 'dev'
Requires-Dist: pre-commit (>=2.6.0) ; extra == 'dev'
Requires-Dist: pre-commit-hooks (>=3.2.0) ; extra == 'dev'
Requires-Dist: twine (>=3.3.0) ; extra == 'dev'
Provides-Extra: test
Requires-Dist: pytest (>=5.4.3) ; extra == 'test'
Requires-Dist: pytest-cov (>=2.9.0) ; extra == 'test'
Provides-Extra: vistool
Requires-Dist: matplotlib (>=3.2.1) ; extra == 'vistool'
Requires-Dist: numpy (>=1.19.5) ; extra == 'vistool'
Requires-Dist: plotly (>=4.9.0) ; extra == 'vistool'
Requires-Dist: PyYAML (>=5.3.1) ; extra == 'vistool'
Requires-Dist: scipy (>=1.4.1) ; extra == 'vistool'
Requires-Dist: tensorboard (>=2.6.0) ; extra == 'vistool'
Requires-Dist: tqdm (>=4.48.2) ; extra == 'vistool'
